justag
