Metadata-Version: 1.0
Name: justag
Version: 0.0.3.2
Summary: Generating JTAG debug hardware from Markdown files.
Home-page: https://github.com/StanfordVLSI/JusTAG
Author: Stanford University
Author-email: UNKNOWN
License: UNKNOWN
Platform: UNKNOWN
